urdu_g2p/__init__.py
urdu_g2p/g2p.py
urdu_g2p/g2p_tokenizer.py
urdu_g2p/vocab.py
urdu_g2p/data/custom.json
urdu_g2p/data/phoneme_map.json
urdu_g2p-2.0.1.dist-info/licenses/LICENSE
urdu_g2p-2.0.1.dist-info/METADATA
urdu_g2p-2.0.1.dist-info/WHEEL
urdu_g2p-2.0.1.dist-info/entry_points.txt
urdu_g2p-2.0.1.dist-info/top_level.txt
urdu_g2p-2.0.1.dist-info/RECORD
