Metadata-Version: 2.4
Name: urdu-g2p
Version: 2.0.1
Summary: High-performance Urdu Grapheme-to-Phoneme converter
Author-email: Humair Munir Awan <humairmunirawan@gmail.com>
License: Urdu G2P - Non-Commercial License
Project-URL: Homepage, https://github.com/humair-m/urdu-g2p
Project-URL: Repository, https://github.com/humair-m/urdu-g2p.git
Project-URL: Issues, https://github.com/humair-m/urdu-g2p/issues
Keywords: urdu,g2p,phoneme,speech-synthesis,nlp
Classifier: Development Status :: 5 - Production/Stable
Classifier: Intended Audience :: Developers
Classifier: Intended Audience :: Science/Research
Classifier: License :: Other/Proprietary License
Classifier: Programming Language :: Python :: 3
Classifier: Topic :: Text Processing :: Linguistic
Classifier: Topic :: Scientific/Engineering :: Artificial Intelligence
Requires-Python: >=3.8
License-File: LICENSE
Dynamic: license-file
